homeworkpy/__init__.py
homeworkpy/homework.py
homeworkpy/tools.py
homeworkpy-0.3.0a0.dist-info/LICENSE
homeworkpy-0.3.0a0.dist-info/WHEEL
homeworkpy-0.3.0a0.dist-info/METADATA
homeworkpy-0.3.0a0.dist-info/RECORD
