Metadata-Version: 2.1
Name: homeworkpy
Version: 0.3.0a0
Summary: An all-in-one pythonic student data representation solution.
Home-page: https://colderinit.github.io/homework-py
License: MIT
Keywords: homework,student,data,representation
Author: Nathan Solis
Author-email: 66754842+colderinit@users.noreply.github.com
Requires-Python: >=3.10,<4.0
Classifier: License :: OSI Approved :: MIT License
Classifier: Programming Language :: Python :: 3
Classifier: Programming Language :: Python :: 3.10
Requires-Dist: beautifulsoup4 (==4.11.1)
Requires-Dist: recurring-ical-events (==1.0.2b0)
Requires-Dist: requests (==2.28.0)
Requires-Dist: rich (==12.4.4)
Project-URL: Bug Tracker, https://github.com/colderinit/homework-py/issues
Project-URL: Documentation, https://colderinit.github.io/homework-py/docs
Project-URL: Repository, https://github.com/colderinit/homework-py
